dataprep_ml/__init__.py
dataprep_ml/base.py
dataprep_ml/cleaners.py
dataprep_ml/helpers.py
dataprep_ml/imputers.py
dataprep_ml/insights.py
dataprep_ml/recommenders.py
dataprep_ml/splitters.py
dataprep_ml-25.2.3.0.dist-info/LICENSE
dataprep_ml-25.2.3.0.dist-info/METADATA
dataprep_ml-25.2.3.0.dist-info/WHEEL
dataprep_ml-25.2.3.0.dist-info/RECORD
