Metadata-Version: 2.1
Name: dataprep-ml
Version: 25.2.3.0
Summary: Automated dataframe analysis for Machine Learning pipelines.
License: GPL-3.0
Author: MindsDB Inc.
Author-email: hello@mindsdb.com
Requires-Python: >=3.8,<3.12
Classifier: License :: OSI Approved :: GNU General Public License v3 (GPLv3)
Classifier: Programming Language :: Python :: 3
Classifier: Programming Language :: Python :: 3.8
Classifier: Programming Language :: Python :: 3.9
Classifier: Programming Language :: Python :: 3.10
Classifier: Programming Language :: Python :: 3.11
Requires-Dist: colorlog (>=6.5.0,<7.0.0)
Requires-Dist: dataclasses-json (>=0.6.3,<0.7.0)
Requires-Dist: numpy (>=1,<2)
Requires-Dist: pandas (>=2,<3)
Requires-Dist: pydantic
Requires-Dist: pydateinfer (==0.3.0)
Requires-Dist: python-dateutil (>=2.1)
Requires-Dist: scipy (>=1.7.3)
Requires-Dist: type-infer (>=0.0.21)
